{
  "url": "https://casertace.net/tutti-i-nomi-fiumi-di-cocaina-invadono-la-provincia-di-caserta-sotto-processo-in-26-lo-spaccio-padre-figlia-e-le-accuse-di-usura/",
  "url_mobile": NaN,
  "title": "TUTTI I NOMI . Fiumi di cocaina invadono la provincia di CASERTA . Sotto processo in 26 . Lo spaccio padre - figlia e le accuse di usura",
  "seendate": "20260315T150000Z",
  "language": "Italian",
  "sourcecountry": "Italy",
  "domain": "casertace.net",
  "content_length": 4487,
  "detected_language": "it",
  "crawled_at": "2026-03-16T14:47:16.729508",
  "hash": "e66eeee97049"
}
