{
  "url": "https://www.eluniversal.com.mx/techbit/asi-son-las-nuevas-alertas-en-redes-de-meta-contra-fraudes/",
  "url_mobile": "https://www.eluniversal.com.mx/techbit/asi-son-las-nuevas-alertas-en-redes-de-meta-contra-fraudes/?outputType=amp",
  "title": "Así son las nuevas alertas en redes de Meta contra fraudes",
  "seendate": "20260313T031500Z",
  "language": "Spanish",
  "sourcecountry": "Mexico",
  "domain": "eluniversal.com.mx",
  "content_length": 5313,
  "detected_language": "es",
  "crawled_at": "2026-03-16T15:15:10.448925",
  "hash": "43ef541efeae"
}
