{
  "url": "http://www.haberler.com/guncel/bahcelievler-de-silahli-soygun-8-supheli-gozaltina-alindi-19646054-haberi/",
  "url_mobile": "https://www.haberler.com/amp/bahcelievler-de-silahli-soygun-8-supheli-gozaltina-alindi-19646054-haberi/",
  "title": "İstanbulda Kuyumcukentten uzun namlulu silahlarla yapılan soyguna ilişkin 8 şüpheli yakalandı",
  "seendate": "20260311T084500Z",
  "language": "Turkish",
  "sourcecountry": "Turkey",
  "domain": "haberler.com",
  "content_length": 1164,
  "detected_language": "tr",
  "crawled_at": "2026-03-16T15:06:17.218094",
  "hash": "de02930e6392"
}
